circuit_designer/__init__.py
circuit_designer/circuit_canvas.py
circuit_designer/circuit_editor.py
circuit_designer/config_dialog.py
circuit_designer/ft_circuit_choice_dialog.py
circuit_designer/gate_palette.py
circuit_designer/gui_main.py
circuit_designer/training_dialog.py
circuit_designer/workflow_bridge.py
circuit_designer/visualization/color_schemes.py
circuit_designer/visualization/device_grid_visualizer.py
circuit_designer/visualization/mapping_visualizer.py
circuit_designer/visualization/surface_code_visualizer.py
circuit_optimization/__init__.py
circuit_optimization/api.py
circuit_optimization/circuit_optimizer.py
circuit_optimization/reward_engine.py
circuit_optimization/rl_env.py
circuit_optimization/utils.py
circuit_optimization/strategies/__init__.py
circuit_optimization/strategies/ml_based.py
circuit_optimization/strategies/rl_based.py
circuit_optimization/strategies/rule_based.py
code_switcher/__init__.py
code_switcher/code_switcher.py
configs/__init__.py
configs/backends.yaml
configs/config_registry.yaml
configs/editor_config.yaml
configs/ft_builder_config.yaml
configs/gates.yaml
configs/hardware.json
configs/ibm_devices.yaml
configs/ionq_devices.yaml
configs/logging.yaml
configs/multi_patch_rl_agent.yaml
configs/optimizer_config.yaml
configs/surface_code_config.yaml
configs/switcher_config.yaml
configs/use_rl_agent.yaml
configs/visualization.yaml
configuration_management/__init__.py
configuration_management/config_manager.py
configuration_management/schema_validator.py
evaluation/__init__.py
evaluation/__main__.py
evaluation/evaluation_framework.py
evaluation/test_surface_code_layouts.py
execution_simulation/__init__.py
execution_simulation/execution_simulator.py
fault_tolerant_circuit_builder/__init__.py
fault_tolerant_circuit_builder/ft_circuit_builder.py
hardware_abstraction/__init__.py
hardware_abstraction/device_abstraction.py
hardware_abstraction/hardware_config_loader.py
logging_results/__init__.py
logging_results/logging_results_manager.py
qcraft-0.1.6.dist-info/METADATA
qcraft-0.1.6.dist-info/WHEEL
qcraft-0.1.6.dist-info/entry_points.txt
qcraft-0.1.6.dist-info/top_level.txt
qcraft-0.1.6.dist-info/RECORD
