Metadata-Version: 2.1
Name: qcraft
Version: 0.1.6
Summary: Qcraft: Quantum Circuit Design, Optimization, and Surface Code Mapping Platform
Author: Debasis Mondal
Requires-Dist: PySide6
Requires-Dist: PyYAML
Requires-Dist: jsonschema
Requires-Dist: networkx
Requires-Dist: matplotlib
Requires-Dist: numpy
Requires-Dist: stable-baselines3
Requires-Dist: scikit-learn
Requires-Dist: pandas
Requires-Dist: torch
Requires-Dist: gymnasium
Requires-Dist: stim
Requires-Dist: pymatching
Requires-Dist: qiskit>=1.0
Requires-Dist: qiskit-aer
Requires-Dist: qiskit-ibm-runtime
Requires-Dist: python-dotenv
